{
  "coloredBottleCount": 8,
  "emptyBottleCount": 2,
  "bottleVolume": 4,
  "bottleList": [
    [
      "blue",
      "lime",
      "brown",
      "brown"
    ],
    [
      "orange",
      "blue",
      "purple",
      "lime"
    ],
    [
      "red",
      "orange",
      "teal",
      "blue"
    ],
    [
      "red",
      "blueGrey",
      "red",
      "blueGrey"
    ],
    [
      "purple",
      "lime",
      "brown",
      "purple"
    ],
    [],
    [
      "lime",
      "brown",
      "purple",
      "teal"
    ],
    [
      "red",
      "blueGrey",
      "orange",
      "teal"
    ],
    [],
    [
      "blueGrey",
      "orange",
      "teal",
      "blue"
    ]
  ],
  "solution": [
    [
      0,
      8
    ],
    [
      6,
      5
    ],
    [
      4,
      6
    ],
    [
      4,
      0
    ],
    [
      0,
      8
    ],
    [
      0,
      8
    ],
    [
      4,
      0
    ],
    [
      6,
      4
    ],
    [
      6,
      4
    ],
    [
      6,
      8
    ],
    [
      0,
      6
    ],
    [
      1,
      6
    ],
    [
      4,
      1
    ],
    [
      0,
      6
    ],
    [
      1,
      4
    ],
    [
      1,
      4
    ],
    [
      1,
      0
    ],
    [
      9,
      0
    ],
    [
      2,
      0
    ],
    [
      9,
      2
    ],
    [
      2,
      5
    ],
    [
      2,
      5
    ],
    [
      7,
      5
    ],
    [
      9,
      2
    ],
    [
      2,
      7
    ],
    [
      7,
      1
    ],
    [
      2,
      7
    ],
    [
      7,
      1
    ],
    [
      7,
      1
    ],
    [
      7,
      9
    ],
    [
      3,
      9
    ],
    [
      3,
      2
    ],
    [
      3,
      9
    ],
    [
      7,
      3
    ],
    [
      3,
      2
    ],
    [
      3,
      2
    ]
  ],
  "level": 3067
}