{
  "coloredBottleCount": 9,
  "emptyBottleCount": 2,
  "bottleVolume": 4,
  "bottleList": [
    [],
    [
      "blue",
      "red",
      "lime",
      "blueGrey"
    ],
    [
      "purple",
      "brown",
      "red",
      "lime"
    ],
    [
      "mahogany",
      "teal",
      "mahogany",
      "teal"
    ],
    [
      "mahogany",
      "purple",
      "blue",
      "brown"
    ],
    [
      "brown",
      "green",
      "green",
      "blueGrey"
    ],
    [
      "blueGrey",
      "green",
      "red",
      "lime"
    ],
    [
      "teal",
      "purple",
      "blue",
      "brown"
    ],
    [
      "lime",
      "blueGrey",
      "green",
      "red"
    ],
    [
      "mahogany",
      "teal",
      "purple",
      "blue"
    ],
    []
  ],
  "solution": [
    [
      8,
      10
    ],
    [
      8,
      0
    ],
    [
      1,
      8
    ],
    [
      6,
      1
    ],
    [
      6,
      10
    ],
    [
      6,
      0
    ],
    [
      8,
      6
    ],
    [
      5,
      6
    ],
    [
      5,
      0
    ],
    [
      6,
      8
    ],
    [
      6,
      8
    ],
    [
      5,
      0
    ],
    [
      8,
      6
    ],
    [
      8,
      6
    ],
    [
      8,
      6
    ],
    [
      1,
      8
    ],
    [
      1,
      8
    ],
    [
      10,
      1
    ],
    [
      2,
      8
    ],
    [
      1,
      2
    ],
    [
      2,
      10
    ],
    [
      1,
      2
    ],
    [
      2,
      10
    ],
    [
      2,
      10
    ],
    [
      2,
      5
    ],
    [
      7,
      5
    ],
    [
      4,
      5
    ],
    [
      7,
      4
    ],
    [
      4,
      1
    ],
    [
      4,
      1
    ],
    [
      9,
      1
    ],
    [
      7,
      4
    ],
    [
      4,
      9
    ],
    [
      9,
      2
    ],
    [
      4,
      9
    ],
    [
      9,
      2
    ],
    [
      9,
      2
    ],
    [
      9,
      7
    ],
    [
      3,
      7
    ],
    [
      3,
      4
    ],
    [
      3,
      7
    ],
    [
      9,
      3
    ],
    [
      3,
      4
    ],
    [
      3,
      4
    ]
  ],
  "hardness": 0,
  "level": 22943
}