{
  "coloredBottleCount": 10,
  "emptyBottleCount": 2,
  "bottleVolume": 4,
  "bottleList": [
    [
      "red",
      "yellow",
      "teal",
      "mahogany"
    ],
    [
      "green",
      "lime",
      "green",
      "purple"
    ],
    [
      "blueGrey",
      "lime",
      "purple",
      "purple"
    ],
    [
      "red",
      "orange",
      "yellow",
      "teal"
    ],
    [
      "red",
      "orange",
      "red",
      "orange"
    ],
    [
      "pink",
      "purple",
      "green",
      "lime"
    ],
    [
      "orange",
      "yellow",
      "teal",
      "mahogany"
    ],
    [
      "mahogany",
      "blueGrey",
      "pink",
      "green"
    ],
    [],
    [
      "yellow",
      "mahogany",
      "blueGrey",
      "pink"
    ],
    [
      "teal",
      "blueGrey",
      "pink",
      "lime"
    ],
    []
  ],
  "solution": [
    [
      2,
      8
    ],
    [
      5,
      11
    ],
    [
      1,
      2
    ],
    [
      2,
      8
    ],
    [
      1,
      5
    ],
    [
      1,
      11
    ],
    [
      8,
      2
    ],
    [
      5,
      1
    ],
    [
      2,
      8
    ],
    [
      2,
      8
    ],
    [
      2,
      11
    ],
    [
      1,
      5
    ],
    [
      10,
      11
    ],
    [
      5,
      1
    ],
    [
      5,
      1
    ],
    [
      8,
      5
    ],
    [
      8,
      5
    ],
    [
      7,
      1
    ],
    [
      5,
      8
    ],
    [
      5,
      8
    ],
    [
      5,
      8
    ],
    [
      7,
      10
    ],
    [
      10,
      5
    ],
    [
      10,
      5
    ],
    [
      9,
      5
    ],
    [
      7,
      10
    ],
    [
      10,
      9
    ],
    [
      9,
      2
    ],
    [
      10,
      9
    ],
    [
      9,
      2
    ],
    [
      9,
      2
    ],
    [
      9,
      7
    ],
    [
      6,
      7
    ],
    [
      0,
      7
    ],
    [
      6,
      0
    ],
    [
      0,
      10
    ],
    [
      0,
      10
    ],
    [
      3,
      10
    ],
    [
      6,
      0
    ],
    [
      0,
      3
    ],
    [
      3,
      9
    ],
    [
      0,
      3
    ],
    [
      3,
      9
    ],
    [
      3,
      9
    ],
    [
      3,
      6
    ],
    [
      4,
      6
    ],
    [
      4,
      0
    ],
    [
      4,
      6
    ],
    [
      3,
      4
    ],
    [
      4,
      0
    ],
    [
      4,
      0
    ]
  ],
  "hardness": 0,
  "level": 8442
}