{
  "coloredBottleCount": 12,
  "emptyBottleCount": 2,
  "bottleVolume": 4,
  "bottleList": [
    [],
    [
      "orange",
      "brown",
      "teal",
      "brown"
    ],
    [
      "yellow",
      "mahogany",
      "blueGrey",
      "red"
    ],
    [
      "yellow",
      "blueGrey",
      "red",
      "lime"
    ],
    [
      "purple",
      "purple",
      "blue",
      "purple"
    ],
    [
      "yellow",
      "mahogany",
      "yellow",
      "mahogany"
    ],
    [
      "mahogany",
      "blueGrey",
      "red",
      "lime"
    ],
    [
      "pink",
      "green",
      "brown",
      "blue"
    ],
    [
      "green",
      "brown",
      "teal",
      "blue"
    ],
    [
      "lime",
      "pink",
      "orange",
      "green"
    ],
    [],
    [
      "teal",
      "teal",
      "purple",
      "blue"
    ],
    [
      "red",
      "pink",
      "orange",
      "green"
    ],
    [
      "blueGrey",
      "lime",
      "pink",
      "orange"
    ]
  ],
  "solution": [
    [
      11,
      10
    ],
    [
      1,
      0
    ],
    [
      4,
      11
    ],
    [
      4,
      10
    ],
    [
      11,
      4
    ],
    [
      11,
      4
    ],
    [
      8,
      10
    ],
    [
      11,
      1
    ],
    [
      1,
      8
    ],
    [
      7,
      10
    ],
    [
      8,
      1
    ],
    [
      1,
      11
    ],
    [
      8,
      1
    ],
    [
      1,
      11
    ],
    [
      1,
      11
    ],
    [
      8,
      1
    ],
    [
      1,
      7
    ],
    [
      7,
      0
    ],
    [
      1,
      7
    ],
    [
      7,
      0
    ],
    [
      7,
      0
    ],
    [
      7,
      8
    ],
    [
      9,
      8
    ],
    [
      12,
      8
    ],
    [
      9,
      12
    ],
    [
      12,
      1
    ],
    [
      12,
      1
    ],
    [
      13,
      1
    ],
    [
      9,
      12
    ],
    [
      12,
      13
    ],
    [
      13,
      7
    ],
    [
      12,
      13
    ],
    [
      13,
      7
    ],
    [
      13,
      7
    ],
    [
      13,
      9
    ],
    [
      6,
      9
    ],
    [
      3,
      9
    ],
    [
      6,
      3
    ],
    [
      3,
      12
    ],
    [
      3,
      12
    ],
    [
      2,
      12
    ],
    [
      6,
      3
    ],
    [
      3,
      2
    ],
    [
      2,
      13
    ],
    [
      3,
      2
    ],
    [
      2,
      13
    ],
    [
      2,
      13
    ],
    [
      2,
      6
    ],
    [
      5,
      6
    ],
    [
      5,
      3
    ],
    [
      5,
      6
    ],
    [
      2,
      5
    ],
    [
      5,
      3
    ],
    [
      5,
      3
    ]
  ],
  "level": 594
}