{
  "coloredBottleCount": 12,
  "emptyBottleCount": 2,
  "bottleVolume": 4,
  "bottleList": [
    [
      "lime",
      "pink",
      "teal",
      "blueGrey"
    ],
    [
      "teal",
      "mahogany",
      "green",
      "blue"
    ],
    [
      "purple",
      "lime",
      "purple",
      "lime"
    ],
    [],
    [
      "pink",
      "blueGrey",
      "mahogany",
      "green"
    ],
    [
      "purple",
      "lime",
      "pink",
      "teal"
    ],
    [
      "yellow",
      "brown",
      "brown",
      "orange"
    ],
    [
      "mahogany",
      "blue",
      "yellow",
      "red"
    ],
    [
      "blue",
      "yellow",
      "red",
      "brown"
    ],
    [],
    [
      "green",
      "yellow",
      "orange",
      "red"
    ],
    [
      "purple",
      "pink",
      "teal",
      "blueGrey"
    ],
    [
      "orange",
      "red",
      "brown",
      "orange"
    ],
    [
      "blueGrey",
      "mahogany",
      "green",
      "blue"
    ]
  ],
  "solution": [
    [
      8,
      9
    ],
    [
      10,
      3
    ],
    [
      12,
      10
    ],
    [
      12,
      9
    ],
    [
      12,
      3
    ],
    [
      3,
      8
    ],
    [
      10,
      12
    ],
    [
      8,
      3
    ],
    [
      6,
      10
    ],
    [
      9,
      6
    ],
    [
      3,
      8
    ],
    [
      10,
      12
    ],
    [
      6,
      9
    ],
    [
      6,
      9
    ],
    [
      8,
      3
    ],
    [
      9,
      6
    ],
    [
      9,
      6
    ],
    [
      10,
      12
    ],
    [
      3,
      8
    ],
    [
      6,
      9
    ],
    [
      8,
      3
    ],
    [
      6,
      9
    ],
    [
      3,
      8
    ],
    [
      6,
      9
    ],
    [
      8,
      3
    ],
    [
      8,
      3
    ],
    [
      7,
      3
    ],
    [
      8,
      10
    ],
    [
      10,
      7
    ],
    [
      7,
      6
    ],
    [
      10,
      7
    ],
    [
      7,
      6
    ],
    [
      7,
      6
    ],
    [
      7,
      8
    ],
    [
      13,
      8
    ],
    [
      1,
      8
    ],
    [
      13,
      1
    ],
    [
      1,
      10
    ],
    [
      1,
      10
    ],
    [
      4,
      10
    ],
    [
      13,
      1
    ],
    [
      1,
      4
    ],
    [
      4,
      7
    ],
    [
      1,
      4
    ],
    [
      4,
      7
    ],
    [
      4,
      7
    ],
    [
      4,
      13
    ],
    [
      0,
      13
    ],
    [
      11,
      13
    ],
    [
      0,
      11
    ],
    [
      11,
      1
    ],
    [
      11,
      1
    ],
    [
      5,
      1
    ],
    [
      0,
      11
    ],
    [
      11,
      5
    ],
    [
      5,
      4
    ],
    [
      11,
      5
    ],
    [
      5,
      4
    ],
    [
      5,
      4
    ],
    [
      5,
      0
    ],
    [
      2,
      0
    ],
    [
      2,
      11
    ],
    [
      2,
      0
    ],
    [
      5,
      2
    ],
    [
      2,
      11
    ],
    [
      2,
      11
    ]
  ],
  "hardness": 0,
  "level": 7781
}