{
  "coloredBottleCount": 11,
  "emptyBottleCount": 2,
  "bottleVolume": 4,
  "bottleList": [
    [
      "orange",
      "blueGrey",
      "teal",
      "blueGrey"
    ],
    [
      "brown",
      "pink",
      "green",
      "lime"
    ],
    [
      "mahogany",
      "purple",
      "blue",
      "teal"
    ],
    [],
    [
      "green",
      "mahogany",
      "orange",
      "purple"
    ],
    [
      "blue",
      "teal",
      "blue",
      "blueGrey"
    ],
    [
      "yellow",
      "pink",
      "green",
      "lime"
    ],
    [
      "teal",
      "blue",
      "purple",
      "blueGrey"
    ],
    [
      "yellow",
      "brown",
      "yellow",
      "brown"
    ],
    [
      "lime",
      "mahogany",
      "orange",
      "purple"
    ],
    [],
    [
      "pink",
      "lime",
      "mahogany",
      "orange"
    ],
    [
      "yellow",
      "brown",
      "pink",
      "green"
    ]
  ],
  "solution": [
    [
      7,
      10
    ],
    [
      7,
      3
    ],
    [
      5,
      10
    ],
    [
      0,
      10
    ],
    [
      5,
      7
    ],
    [
      5,
      0
    ],
    [
      7,
      5
    ],
    [
      7,
      5
    ],
    [
      0,
      7
    ],
    [
      2,
      0
    ],
    [
      2,
      5
    ],
    [
      0,
      7
    ],
    [
      0,
      7
    ],
    [
      0,
      10
    ],
    [
      2,
      3
    ],
    [
      9,
      3
    ],
    [
      4,
      3
    ],
    [
      9,
      4
    ],
    [
      4,
      0
    ],
    [
      4,
      0
    ],
    [
      11,
      0
    ],
    [
      9,
      4
    ],
    [
      4,
      11
    ],
    [
      11,
      2
    ],
    [
      4,
      11
    ],
    [
      11,
      2
    ],
    [
      11,
      2
    ],
    [
      11,
      9
    ],
    [
      1,
      9
    ],
    [
      6,
      9
    ],
    [
      1,
      6
    ],
    [
      6,
      4
    ],
    [
      6,
      4
    ],
    [
      12,
      4
    ],
    [
      1,
      6
    ],
    [
      6,
      12
    ],
    [
      12,
      11
    ],
    [
      6,
      12
    ],
    [
      12,
      11
    ],
    [
      12,
      11
    ],
    [
      12,
      1
    ],
    [
      8,
      1
    ],
    [
      8,
      6
    ],
    [
      8,
      1
    ],
    [
      12,
      8
    ],
    [
      8,
      6
    ],
    [
      8,
      6
    ]
  ],
  "hardness": 0,
  "level": 35844
}