{
  "coloredBottleCount": 10,
  "emptyBottleCount": 2,
  "bottleVolume": 4,
  "bottleList": [
    [
      "orange",
      "yellow",
      "lime",
      "green"
    ],
    [
      "blue",
      "orange",
      "teal",
      "yellow"
    ],
    [
      "mahogany",
      "blue",
      "orange",
      "teal"
    ],
    [
      "green",
      "blueGrey",
      "blueGrey",
      "purple"
    ],
    [
      "blueGrey",
      "blueGrey",
      "brown",
      "purple"
    ],
    [
      "mahogany",
      "orange",
      "teal",
      "yellow"
    ],
    [],
    [
      "yellow",
      "lime",
      "green",
      "purple"
    ],
    [],
    [
      "mahogany",
      "blue",
      "mahogany",
      "blue"
    ],
    [
      "lime",
      "brown",
      "purple",
      "brown"
    ],
    [
      "teal",
      "lime",
      "green",
      "brown"
    ]
  ],
  "solution": [
    [
      4,
      8
    ],
    [
      10,
      6
    ],
    [
      3,
      10
    ],
    [
      10,
      8
    ],
    [
      4,
      6
    ],
    [
      3,
      4
    ],
    [
      8,
      10
    ],
    [
      3,
      4
    ],
    [
      10,
      8
    ],
    [
      10,
      8
    ],
    [
      6,
      10
    ],
    [
      7,
      8
    ],
    [
      10,
      6
    ],
    [
      10,
      6
    ],
    [
      11,
      6
    ],
    [
      7,
      11
    ],
    [
      11,
      3
    ],
    [
      11,
      3
    ],
    [
      0,
      3
    ],
    [
      7,
      11
    ],
    [
      11,
      0
    ],
    [
      0,
      10
    ],
    [
      11,
      0
    ],
    [
      0,
      10
    ],
    [
      0,
      10
    ],
    [
      0,
      7
    ],
    [
      1,
      7
    ],
    [
      5,
      7
    ],
    [
      1,
      5
    ],
    [
      5,
      11
    ],
    [
      5,
      11
    ],
    [
      2,
      11
    ],
    [
      1,
      5
    ],
    [
      5,
      2
    ],
    [
      2,
      0
    ],
    [
      5,
      2
    ],
    [
      2,
      0
    ],
    [
      2,
      0
    ],
    [
      2,
      1
    ],
    [
      9,
      1
    ],
    [
      9,
      5
    ],
    [
      9,
      1
    ],
    [
      2,
      9
    ],
    [
      9,
      5
    ],
    [
      9,
      5
    ]
  ],
  "hardness": 0,
  "level": 26938
}