{
  "coloredBottleCount": 11,
  "emptyBottleCount": 2,
  "bottleVolume": 4,
  "bottleList": [
    [
      "lime",
      "orange",
      "red",
      "brown"
    ],
    [],
    [],
    [
      "mahogany",
      "blueGrey",
      "purple",
      "teal"
    ],
    [
      "purple",
      "brown",
      "lime",
      "orange"
    ],
    [
      "red",
      "yellow",
      "green",
      "yellow"
    ],
    [
      "blueGrey",
      "teal",
      "brown",
      "lime"
    ],
    [
      "teal",
      "brown",
      "lime",
      "orange"
    ],
    [
      "mahogany",
      "pink",
      "blueGrey",
      "purple"
    ],
    [
      "mahogany",
      "pink",
      "mahogany",
      "pink"
    ],
    [
      "green",
      "yellow",
      "green",
      "yellow"
    ],
    [
      "pink",
      "blueGrey",
      "purple",
      "teal"
    ],
    [
      "orange",
      "red",
      "green",
      "red"
    ]
  ],
  "solution": [
    [
      5,
      1
    ],
    [
      0,
      2
    ],
    [
      10,
      1
    ],
    [
      10,
      5
    ],
    [
      10,
      1
    ],
    [
      5,
      10
    ],
    [
      5,
      10
    ],
    [
      5,
      1
    ],
    [
      12,
      0
    ],
    [
      10,
      12
    ],
    [
      0,
      5
    ],
    [
      12,
      10
    ],
    [
      12,
      10
    ],
    [
      12,
      0
    ],
    [
      0,
      5
    ],
    [
      0,
      5
    ],
    [
      0,
      12
    ],
    [
      7,
      12
    ],
    [
      4,
      12
    ],
    [
      7,
      4
    ],
    [
      4,
      0
    ],
    [
      4,
      0
    ],
    [
      6,
      0
    ],
    [
      7,
      4
    ],
    [
      4,
      6
    ],
    [
      6,
      2
    ],
    [
      4,
      6
    ],
    [
      6,
      2
    ],
    [
      6,
      2
    ],
    [
      6,
      7
    ],
    [
      11,
      7
    ],
    [
      3,
      7
    ],
    [
      11,
      3
    ],
    [
      3,
      4
    ],
    [
      3,
      4
    ],
    [
      8,
      4
    ],
    [
      11,
      3
    ],
    [
      3,
      8
    ],
    [
      8,
      6
    ],
    [
      3,
      8
    ],
    [
      8,
      6
    ],
    [
      8,
      6
    ],
    [
      8,
      11
    ],
    [
      9,
      11
    ],
    [
      9,
      3
    ],
    [
      9,
      11
    ],
    [
      8,
      9
    ],
    [
      9,
      3
    ],
    [
      9,
      3
    ]
  ],
  "hardness": 51,
  "level": 5504
}