{
  "coloredBottleCount": 10,
  "emptyBottleCount": 2,
  "bottleVolume": 4,
  "bottleList": [
    [
      "pink",
      "brown",
      "orange",
      "brown"
    ],
    [
      "lime",
      "blueGrey",
      "lime",
      "blueGrey"
    ],
    [
      "blueGrey",
      "red",
      "teal",
      "blue"
    ],
    [
      "blue",
      "orange",
      "pink",
      "purple"
    ],
    [],
    [
      "teal",
      "orange",
      "purple",
      "yellow"
    ],
    [
      "yellow",
      "pink",
      "yellow",
      "brown"
    ],
    [
      "purple",
      "yellow",
      "brown",
      "pink"
    ],
    [],
    [
      "red",
      "blue",
      "orange",
      "purple"
    ],
    [
      "lime",
      "blueGrey",
      "red",
      "teal"
    ],
    [
      "lime",
      "red",
      "teal",
      "blue"
    ]
  ],
  "solution": [
    [
      0,
      8
    ],
    [
      0,
      4
    ],
    [
      6,
      0
    ],
    [
      0,
      8
    ],
    [
      0,
      8
    ],
    [
      7,
      0
    ],
    [
      7,
      8
    ],
    [
      6,
      7
    ],
    [
      6,
      0
    ],
    [
      7,
      6
    ],
    [
      7,
      6
    ],
    [
      5,
      6
    ],
    [
      3,
      5
    ],
    [
      3,
      0
    ],
    [
      5,
      7
    ],
    [
      5,
      7
    ],
    [
      9,
      7
    ],
    [
      3,
      5
    ],
    [
      5,
      9
    ],
    [
      9,
      4
    ],
    [
      5,
      9
    ],
    [
      9,
      4
    ],
    [
      9,
      4
    ],
    [
      9,
      3
    ],
    [
      2,
      3
    ],
    [
      11,
      3
    ],
    [
      2,
      11
    ],
    [
      11,
      5
    ],
    [
      11,
      5
    ],
    [
      10,
      5
    ],
    [
      2,
      11
    ],
    [
      11,
      10
    ],
    [
      10,
      9
    ],
    [
      11,
      10
    ],
    [
      10,
      9
    ],
    [
      10,
      9
    ],
    [
      10,
      2
    ],
    [
      1,
      2
    ],
    [
      1,
      11
    ],
    [
      1,
      2
    ],
    [
      10,
      1
    ],
    [
      1,
      11
    ],
    [
      1,
      11
    ]
  ],
  "hardness": 0,
  "level": 18784
}