{
  "coloredBottleCount": 12,
  "emptyBottleCount": 2,
  "bottleVolume": 4,
  "bottleList": [
    [
      "teal",
      "mahogany",
      "teal",
      "mahogany"
    ],
    [
      "red",
      "brown",
      "blue",
      "green"
    ],
    [
      "purple",
      "red",
      "brown",
      "blue"
    ],
    [
      "orange",
      "brown",
      "blue",
      "green"
    ],
    [],
    [
      "blue",
      "yellow",
      "blueGrey",
      "green"
    ],
    [
      "lime",
      "blueGrey",
      "lime",
      "pink"
    ],
    [
      "yellow",
      "lime",
      "lime",
      "pink"
    ],
    [
      "blueGrey",
      "blueGrey",
      "pink",
      "yellow"
    ],
    [
      "brown",
      "green",
      "yellow",
      "pink"
    ],
    [],
    [
      "teal",
      "mahogany",
      "purple",
      "orange"
    ],
    [
      "mahogany",
      "purple",
      "orange",
      "red"
    ],
    [
      "teal",
      "purple",
      "orange",
      "red"
    ]
  ],
  "solution": [
    [
      6,
      4
    ],
    [
      5,
      10
    ],
    [
      7,
      4
    ],
    [
      6,
      7
    ],
    [
      6,
      5
    ],
    [
      7,
      6
    ],
    [
      7,
      6
    ],
    [
      7,
      6
    ],
    [
      8,
      7
    ],
    [
      8,
      4
    ],
    [
      5,
      8
    ],
    [
      5,
      8
    ],
    [
      7,
      5
    ],
    [
      9,
      4
    ],
    [
      5,
      9
    ],
    [
      9,
      7
    ],
    [
      5,
      9
    ],
    [
      9,
      7
    ],
    [
      9,
      7
    ],
    [
      9,
      10
    ],
    [
      1,
      10
    ],
    [
      3,
      10
    ],
    [
      1,
      3
    ],
    [
      3,
      5
    ],
    [
      3,
      5
    ],
    [
      2,
      5
    ],
    [
      1,
      3
    ],
    [
      3,
      2
    ],
    [
      2,
      9
    ],
    [
      3,
      2
    ],
    [
      2,
      9
    ],
    [
      2,
      9
    ],
    [
      2,
      1
    ],
    [
      12,
      1
    ],
    [
      13,
      1
    ],
    [
      12,
      13
    ],
    [
      13,
      3
    ],
    [
      13,
      3
    ],
    [
      11,
      3
    ],
    [
      12,
      13
    ],
    [
      13,
      11
    ],
    [
      11,
      2
    ],
    [
      13,
      11
    ],
    [
      11,
      2
    ],
    [
      11,
      2
    ],
    [
      11,
      12
    ],
    [
      0,
      12
    ],
    [
      0,
      13
    ],
    [
      0,
      12
    ],
    [
      11,
      0
    ],
    [
      0,
      13
    ],
    [
      0,
      13
    ]
  ],
  "hardness": 1,
  "level": 6600
}