{
  "coloredBottleCount": 8,
  "emptyBottleCount": 2,
  "bottleVolume": 4,
  "bottleList": [
    [
      "teal",
      "orange",
      "blueGrey",
      "purple"
    ],
    [
      "brown",
      "teal",
      "brown",
      "teal"
    ],
    [
      "orange",
      "purple",
      "blue",
      "green"
    ],
    [
      "purple",
      "blue",
      "lime",
      "lime"
    ],
    [
      "brown",
      "teal",
      "orange",
      "blueGrey"
    ],
    [],
    [
      "brown",
      "orange",
      "blueGrey",
      "purple"
    ],
    [
      "green",
      "green",
      "lime",
      "blueGrey"
    ],
    [],
    [
      "blue",
      "green",
      "blue",
      "lime"
    ]
  ],
  "solution": [
    [
      3,
      5
    ],
    [
      7,
      8
    ],
    [
      7,
      3
    ],
    [
      3,
      5
    ],
    [
      9,
      3
    ],
    [
      3,
      5
    ],
    [
      3,
      5
    ],
    [
      9,
      3
    ],
    [
      9,
      7
    ],
    [
      2,
      7
    ],
    [
      3,
      2
    ],
    [
      2,
      9
    ],
    [
      3,
      2
    ],
    [
      2,
      9
    ],
    [
      2,
      9
    ],
    [
      2,
      3
    ],
    [
      0,
      3
    ],
    [
      6,
      3
    ],
    [
      0,
      6
    ],
    [
      6,
      8
    ],
    [
      6,
      8
    ],
    [
      4,
      8
    ],
    [
      0,
      6
    ],
    [
      6,
      4
    ],
    [
      4,
      2
    ],
    [
      6,
      4
    ],
    [
      4,
      2
    ],
    [
      4,
      2
    ],
    [
      4,
      0
    ],
    [
      1,
      0
    ],
    [
      1,
      6
    ],
    [
      1,
      0
    ],
    [
      4,
      1
    ],
    [
      1,
      6
    ],
    [
      1,
      6
    ]
  ],
  "level": 1643
}