{
  "level": 21485,
  "coloredBottleCount": 11,
  "emptyBottleCount": 1,
  "bottleVolume": 4,
  "bottleList": [
    [
      "purple",
      "green",
      "purple",
      "lime"
    ],
    [
      "yellow",
      "teal",
      "blue",
      "orange"
    ],
    [
      "mahogany",
      "teal",
      "orange",
      "blue"
    ],
    [
      "pink",
      "lime",
      "blueGrey",
      "green"
    ],
    [
      "blueGrey",
      "green",
      "lime",
      "blueGrey"
    ],
    [
      "yellow",
      "yellow",
      "teal",
      "yellow"
    ],
    [
      "blue",
      "orange",
      "orange",
      "mahogany"
    ],
    [],
    [
      "teal",
      "mahogany",
      "mahogany",
      "blue"
    ],
    [
      "red",
      "pink",
      "pink",
      "blueGrey"
    ],
    [
      "green",
      "purple",
      "lime",
      "purple"
    ],
    [
      "red",
      "red",
      "pink",
      "red"
    ]
  ],
  "solution": []
}