{
  "coloredBottleCount": 11,
  "emptyBottleCount": 2,
  "bottleVolume": 4,
  "bottleList": [
    [
      "blueGrey",
      "brown",
      "lime",
      "brown"
    ],
    [
      "orange",
      "mahogany",
      "orange",
      "mahogany"
    ],
    [
      "orange",
      "teal",
      "red",
      "blue"
    ],
    [
      "blue",
      "purple",
      "pink",
      "blueGrey"
    ],
    [
      "lime",
      "green",
      "lime",
      "green"
    ],
    [],
    [
      "red",
      "purple",
      "pink",
      "blueGrey"
    ],
    [
      "teal",
      "blue",
      "purple",
      "pink"
    ],
    [
      "purple",
      "blueGrey",
      "green",
      "lime"
    ],
    [],
    [
      "mahogany",
      "teal",
      "red",
      "blue"
    ],
    [
      "orange",
      "mahogany",
      "teal",
      "red"
    ],
    [
      "pink",
      "green",
      "brown",
      "brown"
    ]
  ],
  "solution": [
    [
      12,
      9
    ],
    [
      4,
      5
    ],
    [
      0,
      12
    ],
    [
      12,
      9
    ],
    [
      4,
      0
    ],
    [
      4,
      5
    ],
    [
      0,
      4
    ],
    [
      0,
      4
    ],
    [
      0,
      12
    ],
    [
      12,
      9
    ],
    [
      12,
      9
    ],
    [
      5,
      12
    ],
    [
      8,
      4
    ],
    [
      12,
      8
    ],
    [
      8,
      5
    ],
    [
      12,
      8
    ],
    [
      8,
      5
    ],
    [
      8,
      5
    ],
    [
      8,
      0
    ],
    [
      3,
      0
    ],
    [
      6,
      0
    ],
    [
      3,
      6
    ],
    [
      6,
      12
    ],
    [
      6,
      12
    ],
    [
      7,
      12
    ],
    [
      3,
      6
    ],
    [
      6,
      7
    ],
    [
      7,
      8
    ],
    [
      6,
      7
    ],
    [
      7,
      8
    ],
    [
      7,
      8
    ],
    [
      7,
      3
    ],
    [
      10,
      3
    ],
    [
      2,
      3
    ],
    [
      10,
      2
    ],
    [
      2,
      6
    ],
    [
      2,
      6
    ],
    [
      11,
      6
    ],
    [
      10,
      2
    ],
    [
      2,
      11
    ],
    [
      11,
      7
    ],
    [
      2,
      11
    ],
    [
      11,
      7
    ],
    [
      11,
      7
    ],
    [
      11,
      10
    ],
    [
      1,
      10
    ],
    [
      1,
      2
    ],
    [
      1,
      10
    ],
    [
      11,
      1
    ],
    [
      1,
      2
    ],
    [
      1,
      2
    ]
  ],
  "hardness": 0,
  "level": 18211
}