{
  "level": 17957,
  "coloredBottleCount": 10,
  "emptyBottleCount": 1,
  "bottleVolume": 4,
  "bottleList": [
    [
      "orange",
      "lime",
      "lime",
      "orange"
    ],
    [
      "teal",
      "orange",
      "red",
      "brown"
    ],
    [
      "brown",
      "red",
      "brown",
      "red"
    ],
    [],
    [
      "mahogany",
      "pink",
      "blueGrey",
      "mahogany"
    ],
    [
      "yellow",
      "yellow",
      "mahogany",
      "yellow"
    ],
    [
      "blueGrey",
      "mahogany",
      "green",
      "green"
    ],
    [
      "yellow",
      "pink",
      "green",
      "blueGrey"
    ],
    [
      "teal",
      "teal",
      "orange",
      "teal"
    ],
    [
      "pink",
      "blueGrey",
      "pink",
      "green"
    ],
    [
      "lime",
      "brown",
      "lime",
      "red"
    ]
  ],
  "solution": []
}