{
  "level": 23349,
  "coloredBottleCount": 10,
  "emptyBottleCount": 1,
  "bottleVolume": 4,
  "bottleList": [
    [],
    [
      "pink",
      "yellow",
      "lime",
      "green"
    ],
    [
      "brown",
      "brown",
      "orange",
      "teal"
    ],
    [
      "purple",
      "purple",
      "pink",
      "purple"
    ],
    [
      "purple",
      "lime",
      "green",
      "yellow"
    ],
    [
      "yellow",
      "pink",
      "lime",
      "green"
    ],
    [
      "orange",
      "brown",
      "orange",
      "teal"
    ],
    [
      "blue",
      "blue",
      "red",
      "blue"
    ],
    [
      "blue",
      "red",
      "teal",
      "teal"
    ],
    [
      "red",
      "orange",
      "red",
      "brown"
    ],
    [
      "lime",
      "green",
      "pink",
      "yellow"
    ]
  ],
  "solution": []
}