{
  "coloredBottleCount": 10,
  "emptyBottleCount": 2,
  "bottleVolume": 4,
  "bottleList": [
    [
      "teal",
      "orange",
      "yellow",
      "mahogany"
    ],
    [
      "green",
      "purple",
      "teal",
      "red"
    ],
    [
      "green",
      "purple",
      "green",
      "purple"
    ],
    [],
    [
      "green",
      "teal",
      "red",
      "orange"
    ],
    [
      "yellow",
      "brown",
      "blueGrey",
      "blue"
    ],
    [],
    [
      "blue",
      "brown",
      "blueGrey",
      "brown"
    ],
    [
      "red",
      "yellow",
      "mahogany",
      "blue"
    ],
    [
      "brown",
      "blue",
      "mahogany",
      "blueGrey"
    ],
    [
      "orange",
      "yellow",
      "mahogany",
      "blueGrey"
    ],
    [
      "purple",
      "teal",
      "red",
      "orange"
    ]
  ],
  "solution": [
    [
      9,
      6
    ],
    [
      9,
      3
    ],
    [
      5,
      9
    ],
    [
      5,
      6
    ],
    [
      7,
      5
    ],
    [
      7,
      6
    ],
    [
      7,
      5
    ],
    [
      9,
      7
    ],
    [
      9,
      7
    ],
    [
      5,
      9
    ],
    [
      5,
      9
    ],
    [
      8,
      7
    ],
    [
      9,
      5
    ],
    [
      9,
      5
    ],
    [
      10,
      6
    ],
    [
      5,
      9
    ],
    [
      5,
      9
    ],
    [
      5,
      9
    ],
    [
      10,
      8
    ],
    [
      8,
      3
    ],
    [
      8,
      3
    ],
    [
      0,
      3
    ],
    [
      10,
      8
    ],
    [
      8,
      0
    ],
    [
      0,
      5
    ],
    [
      8,
      0
    ],
    [
      0,
      5
    ],
    [
      0,
      5
    ],
    [
      0,
      10
    ],
    [
      11,
      10
    ],
    [
      4,
      10
    ],
    [
      11,
      4
    ],
    [
      4,
      8
    ],
    [
      4,
      8
    ],
    [
      1,
      8
    ],
    [
      11,
      4
    ],
    [
      4,
      1
    ],
    [
      1,
      0
    ],
    [
      4,
      1
    ],
    [
      1,
      0
    ],
    [
      1,
      0
    ],
    [
      1,
      11
    ],
    [
      2,
      11
    ],
    [
      2,
      4
    ],
    [
      2,
      11
    ],
    [
      1,
      2
    ],
    [
      2,
      4
    ],
    [
      2,
      4
    ]
  ],
  "hardness": 0,
  "level": 31147
}