{
  "level": 28937,
  "coloredBottleCount": 9,
  "emptyBottleCount": 1,
  "bottleVolume": 4,
  "bottleList": [
    [
      "green",
      "purple",
      "yellow",
      "green"
    ],
    [
      "red",
      "orange",
      "orange",
      "teal"
    ],
    [
      "teal",
      "red",
      "lime",
      "lime"
    ],
    [
      "pink",
      "brown",
      "yellow",
      "brown"
    ],
    [
      "purple",
      "brown",
      "purple",
      "yellow"
    ],
    [
      "pink",
      "pink",
      "green",
      "pink"
    ],
    [
      "red",
      "teal",
      "orange",
      "lime"
    ],
    [
      "brown",
      "green",
      "purple",
      "yellow"
    ],
    [],
    [
      "orange",
      "lime",
      "teal",
      "red"
    ]
  ],
  "solution": []
}